MANIFEST.in
README.rst
setup.py
brink/__init__.py
brink/client.py
brink/exceptions.py
python_brink.egg-info/PKG-INFO
python_brink.egg-info/SOURCES.txt
python_brink.egg-info/dependency_links.txt
python_brink.egg-info/not-zip-safe
python_brink.egg-info/requires.txt
python_brink.egg-info/top_level.txt