Metadata-Version: 1.1
Name: python-brink
Version: 0.0.1
Summary: A python wrapper to the brink api
Home-page: https://github.com/Miller-Media/python-brink
Author: Kevin Carwile
Author-email: kevin@miller-media.com
License: MIT
Platform: UNKNOWN
Classifier: Development Status :: 3 - Alpha
Classifier: Intended Audience :: Developers
Classifier: License :: OSI Approved :: MIT License
Classifier: Operating System :: OS Independent
Classifier: Programming Language :: Python
Classifier: Programming Language :: Python :: 2.6
Classifier: Programming Language :: Python :: 2.7
Classifier: Programming Language :: Python :: 3.3
Classifier: Programming Language :: Python :: 3.4
Classifier: Programming Language :: Python :: 3.5
